{
  "status": "snapshot",
  "snapshotOnly": true,
  "generatedAt": "2026-05-30T21:19:31+03:00",
  "note": "Static fallback for feedback-dashboard.html when poanta-api /v1/ops/status is unavailable.",
  "reports": {
    "liveAuditor": {
      "status": "ok",
      "checkedAt": "2026-05-30T21:19:28+03:00",
      "url": "feed.json",
      "updatedAt": "2026-05-30T20:17:24+02:00",
      "items": 241,
      "top": [
        {
          "publishedAt": "2026-05-30T21:10:51+03:00",
          "source": "The Jerusalem Post - Middle East",
          "headline": "מיליציות פרו־איראניות בעיראק מציעות למסור נשק לעצמן",
          "takeaway": "בגדד מתקשה לפרק מיליציות כשהמסלול הרשמי משאיר את הנשק אצל אותן רשתות כוח.",
          "url": "https://www.jpost.com/middle-east/article-897799"
        },
        {
          "publishedAt": "2026-05-30T21:10:03+03:00",
          "source": "וואלה TECH - כל הכתבות",
          "headline": "חשבון האינסטגרם של נתניהו צבר אלפי עוקבים חשודים בן לילה",
          "takeaway": "מספר עוקבים מנופח יכול להפוך לכלי תעמולה אם הציבור לא יודע מי שילם עליו.",
          "url": "https://tech.walla.co.il/item/3841880"
        },
        {
          "publishedAt": "2026-05-30T21:09:35+03:00",
          "source": "וואלה ספורט - ספורט אמריקאי",
          "headline": "קארי צ׳מפיון מאשימה את ה-WNBA בהגנה מוגזמת על קייטלין קלארק",
          "takeaway": "ככל שקלארק הופכת לפנים של הליגה, כל שריקה לטובתה נמדדת גם כמבחן אמינות של ה-WNBA.",
          "url": "https://sports.walla.co.il/item/3841881"
        },
        {
          "publishedAt": "2026-05-30T21:06:00+03:00",
          "source": "mako סלבס - ראשי",
          "headline": "אמילי דמארי ודניאל עמית קבעו חתונה לאוגוסט",
          "takeaway": "דמארי ממשיכה להפוך את החיים שאחרי השבי לסיפור זוגי וציבורי, לא רק אישי.",
          "url": "https://www.mako.co.il/entertainment-celebs/local-2026/Article-8bfcc6f08f97e91027.htm"
        },
        {
          "publishedAt": "2026-05-30T21:00:00+03:00",
          "source": "גלובס - שוק ההון",
          "headline": "משקיעים פרטיים מפסידים תשואה כי הם לא מחזיקים מניות מנצחות מספיק זמן",
          "takeaway": "הבעיה של משקיעים רבים אינה למצוא מניה מנצחת, אלא להחזיק בה כשהרווח כבר מפתה למכור.",
          "url": "https://www.globes.co.il/news/article.aspx?did=1001544279#utm_source=RSS"
        },
        {
          "publishedAt": "2026-05-30T20:50:56+03:00",
          "source": "ישראל היום - כל הכתבות",
          "headline": "קטאר תיאמה עם איראן מעבר מיכליות דרך הורמוז",
          "takeaway": "גם תחת לחץ אמריקני, קטאר ממשיכה לקנות שקט ימי מול איראן כדי לשמור על יצוא האנרגיה שלה.",
          "url": "https://www.israelhayom.co.il/news/world-news/middle-east/article/20650582"
        },
        {
          "publishedAt": "2026-05-30T20:36:32+03:00",
          "source": "הארץ - חדשות",
          "headline": "המחאות נגד הממשלה נמשכו כשירי מלבנון ביטל מוקדים בצפון",
          "takeaway": "המחאה הפוליטית כבר מתנהלת בתוך שגרת מלחמה שבה גם עצרת אזרחית תלויה במצב הביטחוני.",
          "url": "https://www.haaretz.co.il/news/politi/2026-05-30/ty-article/0000019e-7988-d12e-afdf-ffbf3a7c0000"
        },
        {
          "publishedAt": "2026-05-30T20:32:59+03:00",
          "source": "The Jerusalem Post - Middle East",
          "headline": "מנהיג האופוזיציה הטורקי המודח הוציא רבבות נגד ארדואן",
          "takeaway": "הקרב על הנהגת האופוזיציה בטורקיה הופך לכלי שמחליש את היריבים של ארדואן מבפנים.",
          "url": "https://www.jpost.com/middle-east/article-897796"
        },
        {
          "publishedAt": "2026-05-30T20:28:18+03:00",
          "source": "Page Six רכילות חו״ל",
          "headline": "ג׳יימי לי קרטיס נפרדת מאחותה קלי שמתה בגיל 69",
          "takeaway": "מאחורי משפחת הכוכבים של קרטיס עומד גם אבל משפחתי אישי שנחשף עכשיו לציבור.",
          "url": "https://pagesix.com/2026/05/30/celebrity-news/jamie-lee-curtis-sister-kelly-lee-dead-at-69/"
        },
        {
          "publishedAt": "2026-05-30T20:15:02+03:00",
          "source": "דה מרקר - כל הכתבות",
          "headline": "סמוטריץ׳ הקפיא את שיקום הצפון אחרי כישלון עסקת הטבות המס",
          "takeaway": "שיקום הצפון הפך מנושא חירום אזרחי למטבע מיקוח במאבק פוליטי על הטבות מס.",
          "url": "https://www.themarker.com/news/politics/2026-05-30/ty-article/.premium/0000019e-79c2-d49e-a7ff-f9e6e56f0000"
        },
        {
          "publishedAt": "2026-05-30T20:04:22+03:00",
          "source": "The Jerusalem Post - Israel News",
          "headline": "ירי חיזבאללה החזיר את נהריה וכרמיאל למרחב הסכנה",
          "takeaway": "הצפון חוזר למצב שבו גם שגרה אזרחית כמו חוף ים יכולה להפוך בתוך רגע לאירוע חירום.",
          "url": "https://www.jpost.com/israel-news/defense-news/article-897797"
        },
        {
          "publishedAt": "2026-05-30T20:04:03+03:00",
          "source": "Al Jazeera RSS מסונן מזרח תיכון",
          "headline": "רופא פלסטיני נהרג בתקיפה ליד בית חולים במרכז עזה",
          "takeaway": "גם בזמן הפסקת אש רשמית, הזירה הפלסטינית ממשיכה לייצר נפגעים אזרחיים וחיכוך בשתי חזיתות.",
          "url": "https://www.aljazeera.com/news/2026/5/30/palestinian-doctor-killed-three-people-injured-in-israeli-attack-on-gaza?traffic_source=rss"
        }
      ],
      "errors": [],
      "warnings": [
        {
          "severity": "warning",
          "code": "stale_foreign_source_view",
          "message": "Latest foreign-source item is older than 60m: 2026-05-30T20:04:03+03:00 (1:15:24.815771 old). Overall feed may still look fresh, but the world/source view can look stuck. Alert only; this does not block or modify the feed by itself.",
          "item": 11,
          "headline": "רופא פלסטיני נהרג בתקיפה ליד בית חולים במרכז עזה",
          "source": "Al Jazeera RSS מסונן מזרח תיכון",
          "url": "https://www.aljazeera.com/news/2026/5/30/palestinian-doctor-killed-three-people-injured-in-israeli-attack-on-gaza?traffic_source=rss"
        }
      ]
    },
    "timingAuditor": {
      "auditor": "timing",
      "status": "fail",
      "checkedAt": "2026-05-30T21:19:30+03:00",
      "eventsChecked": 2000,
      "clock": "publishedAt_fallback_seenAt",
      "thresholdsMinutes": {
        "all": 25,
        "ביטחון": 25,
        "פוליטיקה": 30,
        "חדשות": 35,
        "פלילים": 40,
        "משפט": 45,
        "כלכלה": 45,
        "צרכנות": 60,
        "רכב": 60,
        "ספורט": 60,
        "אקטואליה בעולם": 60,
        "דעות": 90,
        "טכנולוגיה": 90,
        "בריאות": 90,
        "תרבות": 120,
        "רכילות": 120,
        "נדל״ן": 120,
        "מזג אוויר": 180,
        "important": 60,
        "foreign": 60,
        "דה מרקר": 120,
        "הארץ": 90,
        "מעריב": 90,
        "מקורות זרים": 60
      },
      "warningMinutes": {
        "all": 15
      },
      "recentItems60m": 9,
      "recentSourceGroups60m": [
        "Page Six רכילות חו״ל",
        "The Jerusalem Post",
        "mako סלבס",
        "גלובס",
        "הארץ",
        "וואלה",
        "ישראל היום"
      ],
      "latestByGroup": {
        "Al Jazeera": {
          "latestAt": "2026-05-30T20:04:03+03:00",
          "headline": "רופא פלסטיני נהרג בתקיפה ליד בית חולים במרכז עזה",
          "source": "Al Jazeera RSS מסונן מזרח תיכון"
        },
        "BBC": {
          "latestAt": "2026-05-30T02:30:33+03:00",
          "headline": "טראמפ סיים דיון על הסכם איראן בלי הכרעה חדשה",
          "source": "BBC World"
        },
        "Bloomberg": {
          "latestAt": "2026-05-26T03:28:00+03:00",
          "headline": "עתיד טאיוואן נשאר מבחן הלחץ המרכזי בין סין לארה״ב",
          "source": "Bloomberg Israel/Iran דרך Google News"
        },
        "CNN": {
          "latestAt": "2026-05-27T07:01:07+03:00",
          "headline": "טראמפ מתקשה למצוא יציאה מדינית מהמלחמה עם איראן",
          "source": "CNN World דרך Google News"
        },
        "Daily Mail TVShowbiz רכילות חו״ל": {
          "latestAt": "2026-05-30T19:30:21+03:00",
          "headline": "כריסטין מקגינס מבהירה שחיי הדייטינג של פאדי כבר לא מעניינים אותה",
          "source": "Daily Mail TVShowbiz רכילות חו״ל"
        },
        "Guardian": {
          "latestAt": "2026-05-30T13:00:16+03:00",
          "headline": "טראמפ מתקרב לעסקת איראן מצומצמת אחרי חודשים של מלחמה",
          "source": "The Guardian Middle East"
        },
        "IMS": {
          "latestAt": "2026-05-30T06:00:00+03:00",
          "headline": "מזג האוויר בירושלים: 14°–25°; עננות חלקית; UV גבוה מאוד בצהריים",
          "source": "השירות המטאורולוגי"
        },
        "Israel National News English": {
          "latestAt": "2026-05-30T02:26:06+03:00",
          "headline": "יוון עצרה חשוד במעקב אחר עיתונאי איראן אינטרנשיונל",
          "source": "Israel National News English"
        },
        "Mirror Celebs רכילות חו״ל": {
          "latestAt": "2026-05-30T19:38:35+03:00",
          "headline": "מייקל לה ול התחתן עם ארוסתו אחרי תשע שנות אירוסין",
          "source": "Mirror Celebs רכילות חו״ל"
        },
        "N12": {
          "latestAt": "2026-05-30T12:30:00+03:00",
          "headline": "שף קנדי הודה שמכר רעלים שסייעו להתאבדויות ברשת",
          "source": "N12 - בעולם"
        },
        "New York Times Middle East": {
          "latestAt": "2026-05-30T16:23:50+03:00",
          "headline": "המזרח התיכון ממתין להכרעת טראמפ על הסכם איראן",
          "source": "New York Times Middle East"
        },
        "Page Six רכילות חו״ל": {
          "latestAt": "2026-05-30T20:28:18+03:00",
          "headline": "ג׳יימי לי קרטיס נפרדת מאחותה קלי שמתה בגיל 69",
          "source": "Page Six רכילות חו״ל"
        },
        "TMI": {
          "latestAt": "2026-05-30T14:01:04+03:00",
          "headline": "מיכל הקטנה ובוחבוט ממשיכים להפוך את הזוגיות לתוכן ציבורי",
          "source": "TMI - חדשות סלבס"
        },
        "The Jerusalem Post": {
          "latestAt": "2026-05-30T21:10:51+03:00",
          "headline": "מיליציות פרו־איראניות בעיראק מציעות למסור נשק לעצמן",
          "source": "The Jerusalem Post - Middle East"
        },
        "mako": {
          "latestAt": "2026-05-30T10:57:00+03:00",
          "headline": "משפיען ארגנטינאי הפך מגן ניו זילנדי לאייקון רשת",
          "source": "mako - דיגיטל Nexter"
        },
        "mako סלבס": {
          "latestAt": "2026-05-30T21:06:00+03:00",
          "headline": "אמילי דמארי ודניאל עמית קבעו חתונה לאוגוסט",
          "source": "mako סלבס - ראשי"
        },
        "ynet": {
          "latestAt": "2026-05-30T19:55:23+03:00",
          "headline": "שף קנדי הודה שמכר ערכות רעל שסייעו להתאבדויות בעולם",
          "source": "ynet - כל ערוץ החדשות"
        },
        "אקטואליה בעולם": {
          "latestAt": "2026-05-30T19:55:23+03:00",
          "headline": "שף קנדי הודה שמכר ערכות רעל שסייעו להתאבדויות בעולם",
          "source": "ynet - כל ערוץ החדשות"
        },
        "ביטחון": {
          "latestAt": "2026-05-30T21:10:51+03:00",
          "headline": "מיליציות פרו־איראניות בעיראק מציעות למסור נשק לעצמן",
          "source": "The Jerusalem Post - Middle East"
        },
        "בריאות": {
          "latestAt": "2026-05-30T19:27:45+03:00",
          "headline": "מחקרים קושרים שינה גרועה לסיכון מוגבר לסרטן בגיל צעיר",
          "source": "ynet - כל ערוץ הבריאות"
        },
        "גלובס": {
          "latestAt": "2026-05-30T21:00:00+03:00",
          "headline": "משקיעים פרטיים מפסידים תשואה כי הם לא מחזיקים מניות מנצחות מספיק זמן",
          "source": "גלובס - שוק ההון"
        },
        "דה מרקר": {
          "latestAt": "2026-05-30T20:15:02+03:00",
          "headline": "סמוטריץ׳ הקפיא את שיקום הצפון אחרי כישלון עסקת הטבות המס",
          "source": "דה מרקר - כל הכתבות"
        },
        "דובר צה״ל": {
          "latestAt": "2026-05-30T16:51:31+03:00",
          "headline": "התרעות ביטחוניות הופעלו בצפון והפרטים נבדקים",
          "source": "דובר צה״ל - טלגרם רשמי"
        },
        "דוברות משטרת ישראל": {
          "latestAt": "2026-05-27T10:17:16+03:00",
          "headline": "עיכוב נהג פרוע בכביש 60 הוביל להפרת סדר בתחנת משטרה",
          "source": "דוברות משטרת ישראל - טלגרם רשמי"
        },
        "דעות": {
          "latestAt": "2026-05-30T20:00:31+03:00",
          "headline": "עו״ד סאוסן זהר קוראת לאחד את הרשימות הערביות בלי להדיר נשים",
          "source": "הארץ - דעות"
        },
        "הארץ": {
          "latestAt": "2026-05-30T20:36:32+03:00",
          "headline": "המחאות נגד הממשלה נמשכו כשירי מלבנון ביטל מוקדים בצפון",
          "source": "הארץ - חדשות"
        },
        "וואלה": {
          "latestAt": "2026-05-30T21:10:03+03:00",
          "headline": "חשבון האינסטגרם של נתניהו צבר אלפי עוקבים חשודים בן לילה",
          "source": "וואלה TECH - כל הכתבות"
        },
        "חדשות": {
          "latestAt": "2026-05-30T17:34:24+03:00",
          "headline": "אוניברסיטת תל אביב פתחה מסלול קבלה לפצועי צה״ל בלי פסיכומטרי",
          "source": "The Jerusalem Post - Israel News"
        },
        "טכנולוגיה": {
          "latestAt": "2026-05-30T21:10:03+03:00",
          "headline": "חשבון האינסטגרם של נתניהו צבר אלפי עוקבים חשודים בן לילה",
          "source": "וואלה TECH - כל הכתבות"
        },
        "ישראל היום": {
          "latestAt": "2026-05-30T20:50:56+03:00",
          "headline": "קטאר תיאמה עם איראן מעבר מיכליות דרך הורמוז",
          "source": "ישראל היום - כל הכתבות"
        },
        "כיפה": {
          "latestAt": "2026-05-29T14:15:00+03:00",
          "headline": "חופים מרכזיים בכנרת נסגרו למבקרים בלי התראה מספקת",
          "source": "כיפה - חדשות"
        },
        "כלכלה": {
          "latestAt": "2026-05-30T21:00:00+03:00",
          "headline": "משקיעים פרטיים מפסידים תשואה כי הם לא מחזיקים מניות מנצחות מספיק זמן",
          "source": "גלובס - שוק ההון"
        },
        "מזג אוויר": {
          "latestAt": "2026-05-30T06:00:00+03:00",
          "headline": "מזג האוויר בירושלים: 14°–25°; עננות חלקית; UV גבוה מאוד בצהריים",
          "source": "השירות המטאורולוגי"
        },
        "מעריב": {
          "latestAt": "2026-05-30T19:57:14+03:00",
          "headline": "אישה נפצעה בינוני מפגיעת רכב ברחוב טשרניחובסקי בחיפה",
          "source": "מעריב - מבזקים"
        },
        "מקור ראשון": {
          "latestAt": "2026-05-30T17:01:05+03:00",
          "headline": "חמאס שיקם שליטה אזרחית בעזה בעזרת זרם הסיוע",
          "source": "מקור ראשון דרך Google News"
        },
        "מקורות זרים": {
          "latestAt": "2026-05-30T20:04:03+03:00",
          "headline": "רופא פלסטיני נהרג בתקיפה ליד בית חולים במרכז עזה",
          "source": "Al Jazeera RSS מסונן מזרח תיכון"
        },
        "משטרה": {
          "latestAt": "2026-05-28T19:38:56+03:00",
          "headline": "המשטרה פיזרה הפרות סדר בצומת בר אילן בירושלים",
          "source": "דוברות משטרת ישראל - טלגרם רשמי"
        },
        "משפט": {
          "latestAt": "2026-05-30T10:52:44+03:00",
          "headline": "פאם בונדי הודתה בשגיאות עריכה בתיקי אפשטיין",
          "source": "ישראל היום - כל הכתבות"
        },
        "נדל״ן": {
          "latestAt": "2026-05-30T14:05:44+03:00",
          "headline": "הסכמי הגג כמעט לא הגיעו לרשויות הערביות",
          "source": "דה מרקר - נדל״ן"
        },
        "ספורט": {
          "latestAt": "2026-05-30T21:09:35+03:00",
          "headline": "קארי צ׳מפיון מאשימה את ה-WNBA בהגנה מוגזמת על קייטלין קלארק",
          "source": "וואלה ספורט - ספורט אמריקאי"
        },
        "סרוגים": {
          "latestAt": "2026-05-29T18:02:28+03:00",
          "headline": "טראמפ מכנס הכרעה סופית על עסקת איראן והורמוז",
          "source": "סרוגים - כל הכתבות"
        },
        "ערוץ 7 / INN עברית": {
          "latestAt": "2026-05-29T17:38:53+03:00",
          "headline": "שלושה כלי רכב התנגשו ליד ניל״י; שניים נפצעו בינוני",
          "source": "ערוץ 7 / INN עברית"
        },
        "פוליטיקה": {
          "latestAt": "2026-05-30T20:36:32+03:00",
          "headline": "המחאות נגד הממשלה נמשכו כשירי מלבנון ביטל מוקדים בצפון",
          "source": "הארץ - חדשות"
        },
        "פלילים": {
          "latestAt": "2026-05-30T13:00:00+03:00",
          "headline": "צעיר נורה למוות בירכא במהלך חגיגת יום הולדת משפחתית",
          "source": "וואלה חדשות"
        },
        "צרכנות": {
          "latestAt": "2026-05-30T18:27:45+03:00",
          "headline": "יעדי קיץ פחות עמוסים באירופה מציעים ירידות מחירים חדות",
          "source": "ישראל היום - כל הכתבות"
        },
        "רכב": {
          "latestAt": "2026-05-30T19:57:14+03:00",
          "headline": "אישה נפצעה בינוני מפגיעת רכב ברחוב טשרניחובסקי בחיפה",
          "source": "מעריב - מבזקים"
        },
        "רכילות": {
          "latestAt": "2026-05-30T21:06:00+03:00",
          "headline": "אמילי דמארי ודניאל עמית קבעו חתונה לאוגוסט",
          "source": "mako סלבס - ראשי"
        },
        "תרבות": {
          "latestAt": "2026-05-30T18:41:05+03:00",
          "headline": "מות גבריאל מוקד מסמן פרידה מעורך שטלטל את הספרות העברית",
          "source": "הארץ - תרבות"
        }
      },
      "errors": [
        {
          "severity": "error",
          "code": "publication_timing_sla",
          "group": "foreign",
          "thresholdMinutes": 60,
          "ageMinutes": 75,
          "latestAt": "2026-05-30T20:04:03+03:00",
          "headline": "רופא פלסטיני נהרג בתקיפה ליד בית חולים במרכז עזה",
          "source": "Al Jazeera RSS מסונן מזרח תיכון",
          "message": "No fresh foreign publication event for 75 minutes; threshold is 60 minutes. Alert Aliza and trigger deterministic rescue without lowering editorial standards.",
          "recommendedAction": "trigger_source_rescue_and_alert_aliza",
          "escalateTo": "aliza"
        },
        {
          "severity": "error",
          "code": "publication_timing_sla",
          "group": "פוליטיקה",
          "thresholdMinutes": 30,
          "ageMinutes": 42,
          "latestAt": "2026-05-30T20:36:32+03:00",
          "headline": "המחאות נגד הממשלה נמשכו כשירי מלבנון ביטל מוקדים בצפון",
          "source": "הארץ - חדשות",
          "message": "No fresh פוליטיקה publication event for 42 minutes; threshold is 30 minutes. Alert Aliza and trigger deterministic rescue without lowering editorial standards.",
          "recommendedAction": "trigger_source_rescue_and_alert_aliza",
          "escalateTo": "aliza"
        },
        {
          "severity": "error",
          "code": "publication_timing_sla",
          "group": "חדשות",
          "thresholdMinutes": 35,
          "ageMinutes": 225,
          "latestAt": "2026-05-30T17:34:24+03:00",
          "headline": "אוניברסיטת תל אביב פתחה מסלול קבלה לפצועי צה״ל בלי פסיכומטרי",
          "source": "The Jerusalem Post - Israel News",
          "message": "No fresh חדשות publication event for 225 minutes; threshold is 35 minutes. Alert Aliza and trigger deterministic rescue without lowering editorial standards.",
          "recommendedAction": "trigger_source_rescue_and_alert_aliza",
          "escalateTo": "aliza"
        },
        {
          "severity": "error",
          "code": "publication_timing_sla",
          "group": "פלילים",
          "thresholdMinutes": 40,
          "ageMinutes": 499,
          "latestAt": "2026-05-30T13:00:00+03:00",
          "headline": "צעיר נורה למוות בירכא במהלך חגיגת יום הולדת משפחתית",
          "source": "וואלה חדשות",
          "message": "No fresh פלילים publication event for 499 minutes; threshold is 40 minutes. Alert Aliza and trigger deterministic rescue without lowering editorial standards.",
          "recommendedAction": "trigger_source_rescue_and_alert_aliza",
          "escalateTo": "aliza"
        },
        {
          "severity": "error",
          "code": "publication_timing_sla",
          "group": "משפט",
          "thresholdMinutes": 45,
          "ageMinutes": 626,
          "latestAt": "2026-05-30T10:52:44+03:00",
          "headline": "פאם בונדי הודתה בשגיאות עריכה בתיקי אפשטיין",
          "source": "ישראל היום - כל הכתבות",
          "message": "No fresh משפט publication event for 626 minutes; threshold is 45 minutes. Alert Aliza and trigger deterministic rescue without lowering editorial standards.",
          "recommendedAction": "trigger_source_rescue_and_alert_aliza",
          "escalateTo": "aliza"
        },
        {
          "severity": "error",
          "code": "publication_timing_sla",
          "group": "צרכנות",
          "thresholdMinutes": 60,
          "ageMinutes": 171,
          "latestAt": "2026-05-30T18:27:45+03:00",
          "headline": "יעדי קיץ פחות עמוסים באירופה מציעים ירידות מחירים חדות",
          "source": "ישראל היום - כל הכתבות",
          "message": "No fresh צרכנות publication event for 171 minutes; threshold is 60 minutes. Alert Aliza and trigger deterministic rescue without lowering editorial standards.",
          "recommendedAction": "trigger_source_rescue_and_alert_aliza",
          "escalateTo": "aliza"
        },
        {
          "severity": "error",
          "code": "publication_timing_sla",
          "group": "רכב",
          "thresholdMinutes": 60,
          "ageMinutes": 82,
          "latestAt": "2026-05-30T19:57:14+03:00",
          "headline": "אישה נפצעה בינוני מפגיעת רכב ברחוב טשרניחובסקי בחיפה",
          "source": "מעריב - מבזקים",
          "message": "No fresh רכב publication event for 82 minutes; threshold is 60 minutes. Alert Aliza and trigger deterministic rescue without lowering editorial standards.",
          "recommendedAction": "trigger_source_rescue_and_alert_aliza",
          "escalateTo": "aliza"
        },
        {
          "severity": "error",
          "code": "publication_timing_sla",
          "group": "אקטואליה בעולם",
          "thresholdMinutes": 60,
          "ageMinutes": 84,
          "latestAt": "2026-05-30T19:55:23+03:00",
          "headline": "שף קנדי הודה שמכר ערכות רעל שסייעו להתאבדויות בעולם",
          "source": "ynet - כל ערוץ החדשות",
          "message": "No fresh אקטואליה בעולם publication event for 84 minutes; threshold is 60 minutes. Alert Aliza and trigger deterministic rescue without lowering editorial standards.",
          "recommendedAction": "trigger_source_rescue_and_alert_aliza",
          "escalateTo": "aliza"
        },
        {
          "severity": "error",
          "code": "publication_timing_sla",
          "group": "בריאות",
          "thresholdMinutes": 90,
          "ageMinutes": 111,
          "latestAt": "2026-05-30T19:27:45+03:00",
          "headline": "מחקרים קושרים שינה גרועה לסיכון מוגבר לסרטן בגיל צעיר",
          "source": "ynet - כל ערוץ הבריאות",
          "message": "No fresh בריאות publication event for 111 minutes; threshold is 90 minutes. Alert Aliza and trigger deterministic rescue without lowering editorial standards.",
          "recommendedAction": "trigger_source_rescue_and_alert_aliza",
          "escalateTo": "aliza"
        },
        {
          "severity": "error",
          "code": "publication_timing_sla",
          "group": "תרבות",
          "thresholdMinutes": 120,
          "ageMinutes": 158,
          "latestAt": "2026-05-30T18:41:05+03:00",
          "headline": "מות גבריאל מוקד מסמן פרידה מעורך שטלטל את הספרות העברית",
          "source": "הארץ - תרבות",
          "message": "No fresh תרבות publication event for 158 minutes; threshold is 120 minutes. Alert Aliza and trigger deterministic rescue without lowering editorial standards.",
          "recommendedAction": "trigger_source_rescue_and_alert_aliza",
          "escalateTo": "aliza"
        },
        {
          "severity": "error",
          "code": "publication_timing_sla",
          "group": "נדל״ן",
          "thresholdMinutes": 120,
          "ageMinutes": 433,
          "latestAt": "2026-05-30T14:05:44+03:00",
          "headline": "הסכמי הגג כמעט לא הגיעו לרשויות הערביות",
          "source": "דה מרקר - נדל״ן",
          "message": "No fresh נדל״ן publication event for 433 minutes; threshold is 120 minutes. Alert Aliza and trigger deterministic rescue without lowering editorial standards.",
          "recommendedAction": "trigger_source_rescue_and_alert_aliza",
          "escalateTo": "aliza"
        },
        {
          "severity": "error",
          "code": "publication_timing_sla",
          "group": "מזג אוויר",
          "thresholdMinutes": 180,
          "ageMinutes": 919,
          "latestAt": "2026-05-30T06:00:00+03:00",
          "headline": "מזג האוויר בירושלים: 14°–25°; עננות חלקית; UV גבוה מאוד בצהריים",
          "source": "השירות המטאורולוגי",
          "message": "No fresh מזג אוויר publication event for 919 minutes; threshold is 180 minutes. Alert Aliza and trigger deterministic rescue without lowering editorial standards.",
          "recommendedAction": "trigger_source_rescue_and_alert_aliza",
          "escalateTo": "aliza"
        },
        {
          "severity": "error",
          "code": "publication_timing_sla",
          "group": "מקורות זרים",
          "thresholdMinutes": 60,
          "ageMinutes": 75,
          "latestAt": "2026-05-30T20:04:03+03:00",
          "headline": "רופא פלסטיני נהרג בתקיפה ליד בית חולים במרכז עזה",
          "source": "Al Jazeera RSS מסונן מזרח תיכון",
          "message": "No fresh מקורות זרים publication event for 75 minutes; threshold is 60 minutes. Alert Aliza and trigger deterministic rescue without lowering editorial standards.",
          "recommendedAction": "trigger_source_rescue_and_alert_aliza",
          "escalateTo": "aliza"
        }
      ],
      "warnings": [],
      "findings": [
        {
          "severity": "error",
          "code": "publication_timing_sla",
          "group": "foreign",
          "thresholdMinutes": 60,
          "ageMinutes": 75,
          "latestAt": "2026-05-30T20:04:03+03:00",
          "headline": "רופא פלסטיני נהרג בתקיפה ליד בית חולים במרכז עזה",
          "source": "Al Jazeera RSS מסונן מזרח תיכון",
          "message": "No fresh foreign publication event for 75 minutes; threshold is 60 minutes. Alert Aliza and trigger deterministic rescue without lowering editorial standards.",
          "recommendedAction": "trigger_source_rescue_and_alert_aliza",
          "escalateTo": "aliza"
        },
        {
          "severity": "error",
          "code": "publication_timing_sla",
          "group": "פוליטיקה",
          "thresholdMinutes": 30,
          "ageMinutes": 42,
          "latestAt": "2026-05-30T20:36:32+03:00",
          "headline": "המחאות נגד הממשלה נמשכו כשירי מלבנון ביטל מוקדים בצפון",
          "source": "הארץ - חדשות",
          "message": "No fresh פוליטיקה publication event for 42 minutes; threshold is 30 minutes. Alert Aliza and trigger deterministic rescue without lowering editorial standards.",
          "recommendedAction": "trigger_source_rescue_and_alert_aliza",
          "escalateTo": "aliza"
        },
        {
          "severity": "error",
          "code": "publication_timing_sla",
          "group": "חדשות",
          "thresholdMinutes": 35,
          "ageMinutes": 225,
          "latestAt": "2026-05-30T17:34:24+03:00",
          "headline": "אוניברסיטת תל אביב פתחה מסלול קבלה לפצועי צה״ל בלי פסיכומטרי",
          "source": "The Jerusalem Post - Israel News",
          "message": "No fresh חדשות publication event for 225 minutes; threshold is 35 minutes. Alert Aliza and trigger deterministic rescue without lowering editorial standards.",
          "recommendedAction": "trigger_source_rescue_and_alert_aliza",
          "escalateTo": "aliza"
        },
        {
          "severity": "error",
          "code": "publication_timing_sla",
          "group": "פלילים",
          "thresholdMinutes": 40,
          "ageMinutes": 499,
          "latestAt": "2026-05-30T13:00:00+03:00",
          "headline": "צעיר נורה למוות בירכא במהלך חגיגת יום הולדת משפחתית",
          "source": "וואלה חדשות",
          "message": "No fresh פלילים publication event for 499 minutes; threshold is 40 minutes. Alert Aliza and trigger deterministic rescue without lowering editorial standards.",
          "recommendedAction": "trigger_source_rescue_and_alert_aliza",
          "escalateTo": "aliza"
        },
        {
          "severity": "error",
          "code": "publication_timing_sla",
          "group": "משפט",
          "thresholdMinutes": 45,
          "ageMinutes": 626,
          "latestAt": "2026-05-30T10:52:44+03:00",
          "headline": "פאם בונדי הודתה בשגיאות עריכה בתיקי אפשטיין",
          "source": "ישראל היום - כל הכתבות",
          "message": "No fresh משפט publication event for 626 minutes; threshold is 45 minutes. Alert Aliza and trigger deterministic rescue without lowering editorial standards.",
          "recommendedAction": "trigger_source_rescue_and_alert_aliza",
          "escalateTo": "aliza"
        },
        {
          "severity": "error",
          "code": "publication_timing_sla",
          "group": "צרכנות",
          "thresholdMinutes": 60,
          "ageMinutes": 171,
          "latestAt": "2026-05-30T18:27:45+03:00",
          "headline": "יעדי קיץ פחות עמוסים באירופה מציעים ירידות מחירים חדות",
          "source": "ישראל היום - כל הכתבות",
          "message": "No fresh צרכנות publication event for 171 minutes; threshold is 60 minutes. Alert Aliza and trigger deterministic rescue without lowering editorial standards.",
          "recommendedAction": "trigger_source_rescue_and_alert_aliza",
          "escalateTo": "aliza"
        },
        {
          "severity": "error",
          "code": "publication_timing_sla",
          "group": "רכב",
          "thresholdMinutes": 60,
          "ageMinutes": 82,
          "latestAt": "2026-05-30T19:57:14+03:00",
          "headline": "אישה נפצעה בינוני מפגיעת רכב ברחוב טשרניחובסקי בחיפה",
          "source": "מעריב - מבזקים",
          "message": "No fresh רכב publication event for 82 minutes; threshold is 60 minutes. Alert Aliza and trigger deterministic rescue without lowering editorial standards.",
          "recommendedAction": "trigger_source_rescue_and_alert_aliza",
          "escalateTo": "aliza"
        },
        {
          "severity": "error",
          "code": "publication_timing_sla",
          "group": "אקטואליה בעולם",
          "thresholdMinutes": 60,
          "ageMinutes": 84,
          "latestAt": "2026-05-30T19:55:23+03:00",
          "headline": "שף קנדי הודה שמכר ערכות רעל שסייעו להתאבדויות בעולם",
          "source": "ynet - כל ערוץ החדשות",
          "message": "No fresh אקטואליה בעולם publication event for 84 minutes; threshold is 60 minutes. Alert Aliza and trigger deterministic rescue without lowering editorial standards.",
          "recommendedAction": "trigger_source_rescue_and_alert_aliza",
          "escalateTo": "aliza"
        },
        {
          "severity": "error",
          "code": "publication_timing_sla",
          "group": "בריאות",
          "thresholdMinutes": 90,
          "ageMinutes": 111,
          "latestAt": "2026-05-30T19:27:45+03:00",
          "headline": "מחקרים קושרים שינה גרועה לסיכון מוגבר לסרטן בגיל צעיר",
          "source": "ynet - כל ערוץ הבריאות",
          "message": "No fresh בריאות publication event for 111 minutes; threshold is 90 minutes. Alert Aliza and trigger deterministic rescue without lowering editorial standards.",
          "recommendedAction": "trigger_source_rescue_and_alert_aliza",
          "escalateTo": "aliza"
        },
        {
          "severity": "error",
          "code": "publication_timing_sla",
          "group": "תרבות",
          "thresholdMinutes": 120,
          "ageMinutes": 158,
          "latestAt": "2026-05-30T18:41:05+03:00",
          "headline": "מות גבריאל מוקד מסמן פרידה מעורך שטלטל את הספרות העברית",
          "source": "הארץ - תרבות",
          "message": "No fresh תרבות publication event for 158 minutes; threshold is 120 minutes. Alert Aliza and trigger deterministic rescue without lowering editorial standards.",
          "recommendedAction": "trigger_source_rescue_and_alert_aliza",
          "escalateTo": "aliza"
        },
        {
          "severity": "error",
          "code": "publication_timing_sla",
          "group": "נדל״ן",
          "thresholdMinutes": 120,
          "ageMinutes": 433,
          "latestAt": "2026-05-30T14:05:44+03:00",
          "headline": "הסכמי הגג כמעט לא הגיעו לרשויות הערביות",
          "source": "דה מרקר - נדל״ן",
          "message": "No fresh נדל״ן publication event for 433 minutes; threshold is 120 minutes. Alert Aliza and trigger deterministic rescue without lowering editorial standards.",
          "recommendedAction": "trigger_source_rescue_and_alert_aliza",
          "escalateTo": "aliza"
        },
        {
          "severity": "error",
          "code": "publication_timing_sla",
          "group": "מזג אוויר",
          "thresholdMinutes": 180,
          "ageMinutes": 919,
          "latestAt": "2026-05-30T06:00:00+03:00",
          "headline": "מזג האוויר בירושלים: 14°–25°; עננות חלקית; UV גבוה מאוד בצהריים",
          "source": "השירות המטאורולוגי",
          "message": "No fresh מזג אוויר publication event for 919 minutes; threshold is 180 minutes. Alert Aliza and trigger deterministic rescue without lowering editorial standards.",
          "recommendedAction": "trigger_source_rescue_and_alert_aliza",
          "escalateTo": "aliza"
        },
        {
          "severity": "error",
          "code": "publication_timing_sla",
          "group": "מקורות זרים",
          "thresholdMinutes": 60,
          "ageMinutes": 75,
          "latestAt": "2026-05-30T20:04:03+03:00",
          "headline": "רופא פלסטיני נהרג בתקיפה ליד בית חולים במרכז עזה",
          "source": "Al Jazeera RSS מסונן מזרח תיכון",
          "message": "No fresh מקורות זרים publication event for 75 minutes; threshold is 60 minutes. Alert Aliza and trigger deterministic rescue without lowering editorial standards.",
          "recommendedAction": "trigger_source_rescue_and_alert_aliza",
          "escalateTo": "aliza"
        }
      ]
    },
    "publicationHealthGate": {
      "gate": "pointa_publication_health_gate",
      "mode": "candidate",
      "status": "ok",
      "liveStatus": "ok",
      "timingStatus": null,
      "blockers": [],
      "liveErrors": [],
      "timingErrors": [],
      "top": [
        {
          "publishedAt": "2026-05-30T21:10:51+03:00",
          "source": "The Jerusalem Post - Middle East",
          "headline": "מיליציות פרו־איראניות בעיראק מציעות למסור נשק לעצמן",
          "takeaway": "בגדד מתקשה לפרק מיליציות כשהמסלול הרשמי משאיר את הנשק אצל אותן רשתות כוח.",
          "url": "https://www.jpost.com/middle-east/article-897799"
        },
        {
          "publishedAt": "2026-05-30T21:10:03+03:00",
          "source": "וואלה TECH - כל הכתבות",
          "headline": "חשבון האינסטגרם של נתניהו צבר אלפי עוקבים חשודים בן לילה",
          "takeaway": "מספר עוקבים מנופח יכול להפוך לכלי תעמולה אם הציבור לא יודע מי שילם עליו.",
          "url": "https://tech.walla.co.il/item/3841880"
        },
        {
          "publishedAt": "2026-05-30T21:09:35+03:00",
          "source": "וואלה ספורט - ספורט אמריקאי",
          "headline": "קארי צ׳מפיון מאשימה את ה-WNBA בהגנה מוגזמת על קייטלין קלארק",
          "takeaway": "ככל שקלארק הופכת לפנים של הליגה, כל שריקה לטובתה נמדדת גם כמבחן אמינות של ה-WNBA.",
          "url": "https://sports.walla.co.il/item/3841881"
        },
        {
          "publishedAt": "2026-05-30T21:06:00+03:00",
          "source": "mako סלבס - ראשי",
          "headline": "אמילי דמארי ודניאל עמית קבעו חתונה לאוגוסט",
          "takeaway": "דמארי ממשיכה להפוך את החיים שאחרי השבי לסיפור זוגי וציבורי, לא רק אישי.",
          "url": "https://www.mako.co.il/entertainment-celebs/local-2026/Article-8bfcc6f08f97e91027.htm"
        },
        {
          "publishedAt": "2026-05-30T21:00:00+03:00",
          "source": "גלובס - שוק ההון",
          "headline": "משקיעים פרטיים מפסידים תשואה כי הם לא מחזיקים מניות מנצחות מספיק זמן",
          "takeaway": "הבעיה של משקיעים רבים אינה למצוא מניה מנצחת, אלא להחזיק בה כשהרווח כבר מפתה למכור.",
          "url": "https://www.globes.co.il/news/article.aspx?did=1001544279#utm_source=RSS"
        }
      ],
      "rule": "No script/agent may report OK if the candidate/public feed still violates visible freshness/quantity SLA."
    },
    "autopilot": {
      "lastCheckedAt": "2026-05-30T21:09:14+03:00",
      "lastStatus": "repair_needed",
      "lastIncidentType": "stage3_waiting_for_editor_results",
      "currentIncidentKey": "top_stale|no_new_top_item_sla,stale_updated_at,too_few_recent_items_sla|2026-05-30T19:36:04+02:00|https://www.jpost.com/middle-east/article-897796",
      "currentIncidentRepeatCount": 2,
      "lastAutomaticAction": "write_batch_results_then_rerun_stage3",
      "loopProtection": {
        "active": false,
        "reason": "",
        "repeatCount": 2
      },
      "lastOkAt": "2026-05-25T17:38:06+03:00",
      "lastStage4StartedAt": "2026-05-30T20:29:11+03:00",
      "lastStage4IncidentKey": "domain_sla|פוליטיקה|2026-05-30T15:58:16+03:00|הקרב על מבקר המדינה מציב את נתניהו מול מועמדות טעונה",
      "lastStage4RunDir": "/root/.openclaw/workspace/projects/poanta-demo/tmp/editor-runs/domain-פוליטיקה-20260530-203028",
      "lastStage3StartedAt": "2026-05-30T21:09:14+03:00",
      "lastStage3IncidentKey": "top_stale|no_new_top_item_sla,stale_updated_at,too_few_recent_items_sla|2026-05-30T19:36:04+02:00|https://www.jpost.com/middle-east/article-897796",
      "lastStage3RunDir": "/root/.openclaw/workspace/projects/poanta-demo/tmp/editor-runs/autopilot-20260530-211117"
    }
  },
  "agents": [
    {
      "id": "live",
      "name": "מבקר חי",
      "status": "ok",
      "summary": "תקין בבדיקה האחרונה 2026-05-30T21:19:28+03:00",
      "checkedAt": "2026-05-30T21:19:28+03:00",
      "findings": [
        {
          "severity": "warning",
          "code": "stale_foreign_source_view",
          "message": "Latest foreign-source item is older than 60m: 2026-05-30T20:04:03+03:00 (1:15:24.815771 old). Overall feed may still look fresh, but the world/source view can look stuck. Alert only; this does not block or modify the feed by itself.",
          "item": 11,
          "headline": "רופא פלסטיני נהרג בתקיפה ליד בית חולים במרכז עזה",
          "source": "Al Jazeera RSS מסונן מזרח תיכון",
          "url": "https://www.aljazeera.com/news/2026/5/30/palestinian-doctor-killed-three-people-injured-in-israeli-attack-on-gaza?traffic_source=rss"
        }
      ]
    },
    {
      "id": "timing",
      "name": "מבקר תזמון",
      "status": "fail",
      "summary": "No fresh foreign publication event for 75 minutes; threshold is 60 minutes. Alert Aliza and trigger deterministic rescue without lowering editorial standards.",
      "checkedAt": "2026-05-30T21:19:30+03:00",
      "findings": [
        {
          "severity": "error",
          "code": "publication_timing_sla",
          "group": "foreign",
          "thresholdMinutes": 60,
          "ageMinutes": 75,
          "latestAt": "2026-05-30T20:04:03+03:00",
          "headline": "רופא פלסטיני נהרג בתקיפה ליד בית חולים במרכז עזה",
          "source": "Al Jazeera RSS מסונן מזרח תיכון",
          "message": "No fresh foreign publication event for 75 minutes; threshold is 60 minutes. Alert Aliza and trigger deterministic rescue without lowering editorial standards.",
          "recommendedAction": "trigger_source_rescue_and_alert_aliza",
          "escalateTo": "aliza"
        },
        {
          "severity": "error",
          "code": "publication_timing_sla",
          "group": "פוליטיקה",
          "thresholdMinutes": 30,
          "ageMinutes": 42,
          "latestAt": "2026-05-30T20:36:32+03:00",
          "headline": "המחאות נגד הממשלה נמשכו כשירי מלבנון ביטל מוקדים בצפון",
          "source": "הארץ - חדשות",
          "message": "No fresh פוליטיקה publication event for 42 minutes; threshold is 30 minutes. Alert Aliza and trigger deterministic rescue without lowering editorial standards.",
          "recommendedAction": "trigger_source_rescue_and_alert_aliza",
          "escalateTo": "aliza"
        },
        {
          "severity": "error",
          "code": "publication_timing_sla",
          "group": "חדשות",
          "thresholdMinutes": 35,
          "ageMinutes": 225,
          "latestAt": "2026-05-30T17:34:24+03:00",
          "headline": "אוניברסיטת תל אביב פתחה מסלול קבלה לפצועי צה״ל בלי פסיכומטרי",
          "source": "The Jerusalem Post - Israel News",
          "message": "No fresh חדשות publication event for 225 minutes; threshold is 35 minutes. Alert Aliza and trigger deterministic rescue without lowering editorial standards.",
          "recommendedAction": "trigger_source_rescue_and_alert_aliza",
          "escalateTo": "aliza"
        },
        {
          "severity": "error",
          "code": "publication_timing_sla",
          "group": "פלילים",
          "thresholdMinutes": 40,
          "ageMinutes": 499,
          "latestAt": "2026-05-30T13:00:00+03:00",
          "headline": "צעיר נורה למוות בירכא במהלך חגיגת יום הולדת משפחתית",
          "source": "וואלה חדשות",
          "message": "No fresh פלילים publication event for 499 minutes; threshold is 40 minutes. Alert Aliza and trigger deterministic rescue without lowering editorial standards.",
          "recommendedAction": "trigger_source_rescue_and_alert_aliza",
          "escalateTo": "aliza"
        },
        {
          "severity": "error",
          "code": "publication_timing_sla",
          "group": "משפט",
          "thresholdMinutes": 45,
          "ageMinutes": 626,
          "latestAt": "2026-05-30T10:52:44+03:00",
          "headline": "פאם בונדי הודתה בשגיאות עריכה בתיקי אפשטיין",
          "source": "ישראל היום - כל הכתבות",
          "message": "No fresh משפט publication event for 626 minutes; threshold is 45 minutes. Alert Aliza and trigger deterministic rescue without lowering editorial standards.",
          "recommendedAction": "trigger_source_rescue_and_alert_aliza",
          "escalateTo": "aliza"
        },
        {
          "severity": "error",
          "code": "publication_timing_sla",
          "group": "צרכנות",
          "thresholdMinutes": 60,
          "ageMinutes": 171,
          "latestAt": "2026-05-30T18:27:45+03:00",
          "headline": "יעדי קיץ פחות עמוסים באירופה מציעים ירידות מחירים חדות",
          "source": "ישראל היום - כל הכתבות",
          "message": "No fresh צרכנות publication event for 171 minutes; threshold is 60 minutes. Alert Aliza and trigger deterministic rescue without lowering editorial standards.",
          "recommendedAction": "trigger_source_rescue_and_alert_aliza",
          "escalateTo": "aliza"
        },
        {
          "severity": "error",
          "code": "publication_timing_sla",
          "group": "רכב",
          "thresholdMinutes": 60,
          "ageMinutes": 82,
          "latestAt": "2026-05-30T19:57:14+03:00",
          "headline": "אישה נפצעה בינוני מפגיעת רכב ברחוב טשרניחובסקי בחיפה",
          "source": "מעריב - מבזקים",
          "message": "No fresh רכב publication event for 82 minutes; threshold is 60 minutes. Alert Aliza and trigger deterministic rescue without lowering editorial standards.",
          "recommendedAction": "trigger_source_rescue_and_alert_aliza",
          "escalateTo": "aliza"
        },
        {
          "severity": "error",
          "code": "publication_timing_sla",
          "group": "אקטואליה בעולם",
          "thresholdMinutes": 60,
          "ageMinutes": 84,
          "latestAt": "2026-05-30T19:55:23+03:00",
          "headline": "שף קנדי הודה שמכר ערכות רעל שסייעו להתאבדויות בעולם",
          "source": "ynet - כל ערוץ החדשות",
          "message": "No fresh אקטואליה בעולם publication event for 84 minutes; threshold is 60 minutes. Alert Aliza and trigger deterministic rescue without lowering editorial standards.",
          "recommendedAction": "trigger_source_rescue_and_alert_aliza",
          "escalateTo": "aliza"
        }
      ]
    },
    {
      "id": "gatekeeper",
      "name": "השוער",
      "status": "ok",
      "summary": "תקין בבדיקה האחרונה",
      "checkedAt": "",
      "findings": []
    },
    {
      "id": "repair",
      "name": "המתקן",
      "status": "unknown",
      "summary": "סטטוס unknown בבדיקה האחרונה",
      "checkedAt": "",
      "findings": []
    }
  ]
}
